vlhmath/__init__.py
vlhmath/eq2.py
vlhmath/eq4.py
vlhmath/trigonometry.py
vlhmath-1.0.0.dist-info/METADATA
vlhmath-1.0.0.dist-info/WHEEL
vlhmath-1.0.0.dist-info/top_level.txt
vlhmath-1.0.0.dist-info/RECORD
